faim_wako_searchfirst/__init__.py
faim_wako_searchfirst/filter.py
faim_wako_searchfirst/main.py
faim_wako_searchfirst/sample.py
faim_wako_searchfirst/segment.py
faim_wako_searchfirst-0.8.0.dist-info/METADATA
faim_wako_searchfirst-0.8.0.dist-info/WHEEL
faim_wako_searchfirst-0.8.0.dist-info/RECORD
