Metadata-Version: 2.3
Name: faim-wako-searchfirst
Version: 0.8.0
Project-URL: Documentation, https://github.com/fmi-faim/faim-wako-searchfirst#readme
Project-URL: Issues, https://github.com/fmi-faim/faim-wako-searchfirst/issues
Project-URL: Source, https://github.com/fmi-faim/faim-wako-searchfirst
Author-email: Jan Eglinger <jan.eglinger@fmi.ch>
License-Expression: MIT
Classifier: Development Status :: 4 - Beta
Classifier: Programming Language :: Python
Classifier: Programming Language :: Python :: 3.8
Classifier: Programming Language :: Python :: 3.9
Classifier: Programming Language :: Python :: 3.10
Classifier: Programming Language :: Python :: 3.11
Classifier: Programming Language :: Python :: Implementation :: CPython
Classifier: Programming Language :: Python :: Implementation :: PyPy
Requires-Python: >=3.8
Requires-Dist: cellpose
Requires-Dist: confuse
Requires-Dist: rich
Requires-Dist: scikit-image
Requires-Dist: tqdm
Requires-Dist: typer
